cmake/FindTaichi.cmake
scripts/linux/cu12x/setup_cuda.py
scripts/linux/cu12x/pyproject.toml
scripts/linux/cu12x/prepare_build_wheel_on_cuda.sh
scripts/linux/cu11x/setup_cuda.py
scripts/linux/cu11x/pyproject.toml
scripts/linux/cu11x/prepare_build_wheel_on_cuda.sh
scripts/linux/cpu/pyproject.toml
scripts/linux/cpu/setup_cpu.py
scripts/linux/cpu/prepare_build_wheel_on_cuda.sh
scripts/win/script_py38.bat
scripts/win/pyproject.toml
scripts/win/script_py311.bat
scripts/win/script_py39.bat
scripts/win/setup.py
scripts/win/win_auto_repair.py
scripts/win/script_py310.bat
brainpylib_cu11x-0.2.8.dist-info/LICENSE
brainpylib_cu11x-0.2.8.dist-info/METADATA
brainpylib_cu11x-0.2.8.dist-info/top_level.txt
brainpylib_cu11x-0.2.8.dist-info/RECORD
brainpylib_cu11x-0.2.8.dist-info/WHEEL
brainpylib/gpu_ops.cpython-39-x86_64-linux-gnu.so
brainpylib/__init__.py
brainpylib/cpu_ops.cpython-39-x86_64-linux-gnu.so
brainpylib/libtaichi_c_api.so
brainpylib_cu11x.libs/libtaichi_c_api-2f98267e.so
brainpylib_cu11x.libs/libcudart-d0da41ae.so.11.8.89
